{"commitInfo":{"timestamp":1716655187715,"userId":"724371199044165","userName":"dsawalka.sawalka92@outlook.com","operation":"MERGE","operationParameters":{"predicate":"[\"(((race_id#22772 = race_id#22687) AND (driver_id#22773 = driver_id#22696)) AND (stop#22774 = stop#22653))\"]","matchedPredicates":"[{\"actionType\":\"update\"}]","statsOnLoad":false,"notMatchedBySourcePredicates":"[]","notMatchedPredicates":"[{\"actionType\":\"insert\"}]"},"notebook":{"notebookId":"299142777800133"},"clusterId":"0503-203142-51g31bv4","readVersion":2,"isolationLevel":"WriteSerializable","isBlindAppend":false,"operationMetrics":{"numTargetRowsCopied":"0","numTargetRowsDeleted":"0","numTargetFilesAdded":"1","numTargetBytesAdded":"4030","numTargetBytesRemoved":"0","numTargetDeletionVectorsAdded":"0","numTargetRowsMatchedUpdated":"0","executionTimeMs":"3035","numTargetRowsInserted":"56","numTargetRowsMatchedDeleted":"0","scanTimeMs":"2104","numTargetRowsUpdated":"0","numOutputRows":"56","numTargetDeletionVectorsRemoved":"0","numTargetRowsNotMatchedBySourceUpdated":"0","numTargetChangeFilesAdded":"0","numSourceRows":"56","numTargetFilesRemoved":"0","numTargetRowsNotMatchedBySourceDeleted":"0","rewriteTimeMs":"757"},"tags":{"noRowsCopied":"true","delta.rowTracking.preserved":"false","restoresDeletedRows":"false"},"engineInfo":"Databricks-Runtime/13.3.x-scala2.12","txnId":"cd081330-4a6c-449d-a49a-376bb49aff24"}}
{"add":{"path":"race_id=1053/part-00000-caf01e7a-6f4c-4228-aebe-42f7a442a544.c000.snappy.parquet","partitionValues":{"race_id":"1053"},"size":4030,"modificationTime":1716655187000,"dataChange":true,"stats":"{\"numRecords\":56,\"minValues\":{\"driver_id\":1,\"stop\":\"1\",\"lap\":1,\"time\":\"15:05:16\",\"duration\":\"1:00.172\",\"milliseconds\":29742,\"ingestion_date\":\"2024-05-25T16:39:44.664Z\",\"data_source\":\"Ergast\",\"file_date\":\"2021-04-18\"},\"maxValues\":{\"driver_id\":854,\"stop\":\"5\",\"lap\":40,\"time\":\"16:36:13\",\"duration\":\"57.601\",\"milliseconds\":1621361,\"ingestion_date\":\"2024-05-25T16:39:44.664Z\",\"data_source\":\"Ergast\",\"file_date\":\"2021-04-18\"},\"nullCount\":{\"driver_id\":0,\"stop\":0,\"lap\":0,\"time\":0,\"duration\":0,\"milliseconds\":0,\"ingestion_date\":0,\"data_source\":0,\"file_date\":0}}","tags":{"INSERTION_TIME":"1716655187000000","MIN_INSERTION_TIME":"1716655187000000","MAX_INSERTION_TIME":"1716655187000000","OPTIMIZE_TARGET_SIZE":"67108864"}}}
